[{"id":1,"fecha":"24-05-20","numeroPedido":23,"sabor":"menta granizada","vaso":"cucurucho","mail":"cucho@gmail.com","precio":304.92},{"id":2,"fecha":"24-05-20","numeroPedido":88,"sabor":"menta granizada","vaso":"cucurucho","mail":"cucho@gmail.com","precio":304.92},{"id":3,"fecha":"24-05-20","numeroPedido":53,"sabor":"menta granizada","vaso":"cucurucho","mail":"cucho@gmail.com","precio":277.2},{"id":4,"fecha":"24-05-20","numeroPedido":4,"sabor":"menta granizada","vaso":"cucurucho","mail":"cucho@gmail.com","precio":277.2},{"id":5,"fecha":"24-05-20","numeroPedido":22,"sabor":"frutilla","vaso":"cucurucho","mail":"cucho@gmail.com","precio":767.7},{"id":6,"fecha":"24-05-20","numeroPedido":67,"sabor":"frutilla","vaso":"cucurucho","mail":"cucho@gmail.com","precio":767.7},{"id":7,"fecha":"24-05-20","numeroPedido":50,"sabor":"frutilla","vaso":"cucurucho","mail":"cucho@gmail.com","precio":767.7},{"id":8,"fecha":"24-05-20","numeroPedido":40,"sabor":"frutilla","vaso":"cucurucho","mail":"cucho@gmail.com","precio":767.7},{"id":9,"fecha":"24-05-20","numeroPedido":89,"sabor":"frutilla","vaso":"cucurucho","mail":"cucho@gmail.com","precio":767.7}]